geojson_shave/__init__.py
geojson_shave/geojson_shave.py
geojson_shave-0.2.0.dist-info/LICENSE
geojson_shave-0.2.0.dist-info/METADATA
geojson_shave-0.2.0.dist-info/WHEEL
geojson_shave-0.2.0.dist-info/entry_points.txt
geojson_shave-0.2.0.dist-info/top_level.txt
geojson_shave-0.2.0.dist-info/RECORD
