Metadata-Version: 2.1
Name: geojson-shave
Version: 0.2.0
Summary: A command-line tool for reducing the size of GeoJSON files.
Author-email: Ben Nour <hello@ben-nour.com>
License: MIT License
Project-URL: homepage, https://github.com/ben-n93/geojson-shave
Project-URL: repository, https://github.com/ben-n93/geojson-shave
Keywords: geojson
Classifier: License :: OSI Approved :: MIT License
Classifier: Programming Language :: Python :: 3
Classifier: Programming Language :: Python :: 3.8
Classifier: Programming Language :: Python :: 3.9
Classifier: Programming Language :: Python :: 3.10
Classifier: Programming Language :: Python :: 3.11
Classifier: Programming Language :: Python :: 3.12
Requires-Python: >=3.8
License-File: LICENSE
Requires-Dist: alive-progress ~=3.1.5
Requires-Dist: humanize ~=4.9.0
